Metadata-Version: 2.1
Name: ipip-ipdb-hp
Version: 0.1.1
Summary: IPIP.net non-officially supported IP database ipdb format parsing library
Home-page: https://github.com/magicbear/ipip-ipdb-hp
Author: MagicBear
Author-email: magicbearmo@gmail.com
License: Apache-2.0
Keywords: ipdb,ipip
Classifier: Programming Language :: Python :: 3
Classifier: License :: OSI Approved :: Apache Software License
Classifier: Operating System :: OS Independent
